Metadata-Version: 2.1
Name: odoo-addon-helpdesk_mgmt_timesheet
Version: 18.0.1.1.1
Requires-Python: >=3.10
Requires-Dist: odoo-addon-helpdesk_mgmt_project==18.0.*
Requires-Dist: odoo-addon-project_timesheet_time_control==18.0.*
Requires-Dist: odoo==18.0.*
Summary: Add HR Timesheet to the tickets for Helpdesk Management.
Home-page: https://github.com/OCA/helpdesk
License: AGPL-3
Author: Aresoltec Canarias, Punt Sistemes, SDi Soluciones Digitales, Solvos, Odoo Community Association (OCA)
Author-email: support@odoo-community.org
Classifier: Programming Language :: Python
Classifier: Framework :: Odoo
Classifier: Framework :: Odoo :: 18.0
Classifier: License :: OSI Approved :: GNU Affero General Public License v3
